coco_lib/__init__.py
coco_lib/bases.py
coco_lib/common.py
coco_lib/imagecaptioning.py
coco_lib/keypointdetection.py
coco_lib/objectdetection.py
coco_lib/panopticsegmentation.py
coco_lib-0.3.0.dist-info/METADATA
coco_lib-0.3.0.dist-info/WHEEL
coco_lib-0.3.0.dist-info/licenses/LICENSE
coco_lib-0.3.0.dist-info/RECORD
