Metadata-Version: 2.4
Name: coco-lib
Version: 0.3.0
Summary: COCO dataset library.
Author-email: Kevin Barnard <kbarnard@mbari.org>
Maintainer-email: Kevin Barnard <kbarnard@mbari.org>
License-Expression: MIT
License-File: LICENSE
Requires-Python: >=3.8
Requires-Dist: dateparser>=1.1.3
Requires-Dist: pydantic>=1.7.4
